yolo8_seg_annotator/__init__.py
yolo8_seg_annotator/main.py
yolov8_seg_annotator-1.1.dist-info/LICENSE
yolov8_seg_annotator-1.1.dist-info/METADATA
yolov8_seg_annotator-1.1.dist-info/WHEEL
yolov8_seg_annotator-1.1.dist-info/entry_points.txt
yolov8_seg_annotator-1.1.dist-info/top_level.txt
yolov8_seg_annotator-1.1.dist-info/RECORD
